porlock/__init__.py
porlock/converters.py
porlock/enums.py
porlock/exceptions.py
porlock/mixins/__init__.py
porlock/mixins/base.py
porlock/mixins/django.py
porlock/rules.py
porlock/snoop.py
porlock-0.0.1.dist-info/LICENSE
porlock-0.0.1.dist-info/WHEEL
porlock-0.0.1.dist-info/METADATA
porlock-0.0.1.dist-info/RECORD
