Metadata-Version: 2.1
Name: porlock
Version: 0.0.1
Summary: Find unwanted visitors by analyzing behavior
License: MIT
Author: David Graves
Author-email: dgraves@thesummitgrp.com
Requires-Python: >=3.8,<4.0
Classifier: License :: OSI Approved :: MIT License
Classifier: Programming Language :: Python :: 3
Classifier: Programming Language :: Python :: 3.8
Classifier: Programming Language :: Python :: 3.9
Classifier: Programming Language :: Python :: 3.10
Classifier: Programming Language :: Python :: 3.11
